aurora_cycler_manager/__init__.py
aurora_cycler_manager/analysis.py
aurora_cycler_manager/config.py
aurora_cycler_manager/cycler_servers.py
aurora_cycler_manager/daemon.py
aurora_cycler_manager/database_funcs.py
aurora_cycler_manager/database_setup.py
aurora_cycler_manager/eclab_harvester.py
aurora_cycler_manager/neware_harvester.py
aurora_cycler_manager/server_manager.py
aurora_cycler_manager/setup_logging.py
aurora_cycler_manager/tomato_converter.py
aurora_cycler_manager/utils.py
aurora_cycler_manager/version.py
aurora_cycler_manager/visualiser/__init__.py
aurora_cycler_manager/visualiser/app.py
aurora_cycler_manager/visualiser/batches.py
aurora_cycler_manager/visualiser/db_batch_edit.py
aurora_cycler_manager/visualiser/db_protocol_edit.py
aurora_cycler_manager/visualiser/db_view.py
aurora_cycler_manager/visualiser/funcs.py
aurora_cycler_manager/visualiser/notifications.py
aurora_cycler_manager/visualiser/samples.py
aurora_cycler_manager/visualiser/startup.py
aurora_cycler_manager/visualiser/assets/clientside.js
aurora_cycler_manager/visualiser/assets/dashAgGridFunctions.js
aurora_cycler_manager/visualiser/assets/favicon.ico
aurora_cycler_manager/visualiser/assets/openbis.svg
aurora_cycler_manager/visualiser/assets/spinner-spin.svg
aurora_cycler_manager/visualiser/assets/spinner-stationary.svg
aurora_cycler_manager/visualiser/assets/styles.css
aurora_cycler_manager-0.8.2.dist-info/entry_points.txt
aurora_cycler_manager-0.8.2.dist-info/licenses/LICENSE
aurora_cycler_manager-0.8.2.dist-info/WHEEL
aurora_cycler_manager-0.8.2.dist-info/METADATA
aurora_cycler_manager-0.8.2.dist-info/RECORD
