Metadata-Version: 2.4
Name: aurora-cycler-manager
Version: 0.8.2
Summary: Battery cycler management, data analysis and visualisation.
Requires-Python: >=3.10
License-File: LICENSE
Requires-Dist: aurora-unicycler>=0.3.1
Requires-Dist: dash>=3.1.0
Requires-Dist: dash_ag_grid>=32.3.0
Requires-Dist: dash_bootstrap_components>=2.0.3
Requires-Dist: dash_mantine_components>=2.1.0
Requires-Dist: dash_resizable_panels>=0.1.0
Requires-Dist: defusedxml>=0.7.1
Requires-Dist: h5py>=3.14.0
Requires-Dist: NewareNDA>=2025.6.2
Requires-Dist: numpy>=2.2.6
Requires-Dist: orjson>=3.11.0
Requires-Dist: pandas>=2.3.1
Requires-Dist: paramiko>=3.5.1
Requires-Dist: platformdirs>=4.3.8
Requires-Dist: python-calamine>=0.4.0
Requires-Dist: pytz>=2025.2
Requires-Dist: scp>=0.15.0
Requires-Dist: tables>=3.10.1
Requires-Dist: tsdownsample>=0.1.4.1
Requires-Dist: waitress>=3.0.2
Requires-Dist: xmltodict>=0.14.2
Requires-Dist: yadg>=6.1.3
Requires-Dist: bumpver>=2025.1131 ; extra == "dev"
Requires-Dist: pre-commit>=4.2.0 ; extra == "dev"
Requires-Dist: pytest>=8.4.1 ; extra == "dev"
Requires-Dist: ruff>=0.12.3 ; extra == "dev"
Provides-Extra: dev
